{
    "sections": [{
        "title": "Retail",
        "href": "#",
        "image-url": "assets/imgs/accordian/retail.jpg"
    }, {
        "title": "Healthcare",
        "href": "#",
        "image-url": "assets/imgs/accordian/healthcare.jpg"
    }, {
        "title": "Automotive",
        "href": "#",
        "image-url": "assets/imgs/accordian/automotive.jpg"
    }, {
        "title": "Manufacturing",
        "href": "#",
        "image-url": "assets/imgs/accordian/manufacturing.jpg"
    }]
}
